<?xml version="1.0" encoding="UTF-8"?>
<dataroot xmlns:od="urn:schemas-microsoft-com:officedata" generated="2013-11-22T03:41:38">
<Chapter2>
<Chapter2_ID>1</Chapter2_ID>
<Track_Number>1</Track_Number>
<Track_Name>Track 1</Track_Name>
<Track_File_Name>TOEFL_iBT_01.mp3</Track_File_Name>
<Track_Image>01.png</Track_Image>
</Chapter2>
<Chapter2>
<Chapter2_ID>2</Chapter2_ID>
<Track_Number>2</Track_Number>
<Track_Name>Track 2</Track_Name>
<Track_File_Name>TOEFL_iBT_02.mp3</Track_File_Name>
<Track_Image>02.png</Track_Image>
</Chapter2>
<Chapter2>
<Chapter2_ID>3</Chapter2_ID>
<Track_Number>3</Track_Number>
<Track_Name>Track 3</Track_Name>
<Track_File_Name>TOEFL_iBT_03.mp3</Track_File_Name>
<Track_Image>03.png</Track_Image>
</Chapter2>
<Chapter2>
<Chapter2_ID>4</Chapter2_ID>
<Track_Number>4</Track_Number>
<Track_Name>Track 4</Track_Name>
<Track_File_Name>TOEFL_iBT_04.mp3</Track_File_Name>
<Track_Image>00.png</Track_Image>
</Chapter2>
<Chapter2>
<Chapter2_ID>5</Chapter2_ID>
<Track_Number>5</Track_Number>
<Track_Name>Track 5</Track_Name>
<Track_File_Name>TOEFL_iBT_05.mp3</Track_File_Name>
<Track_Image>04.png</Track_Image>
</Chapter2>
<Chapter2>
<Chapter2_ID>6</Chapter2_ID>
<Track_Number>6</Track_Number>
<Track_Name>Track 6</Track_Name>
<Track_File_Name>TOEFL_iBT_06.mp3</Track_File_Name>
<Track_Image>00.png</Track_Image>
</Chapter2>
<Chapter2>
<Chapter2_ID>7</Chapter2_ID>
<Track_Number>7</Track_Number>
<Track_Name>Track 7</Track_Name>
<Track_File_Name>TOEFL_iBT_07.mp3</Track_File_Name>
<Track_Image>05.png</Track_Image>
</Chapter2>
<Chapter2>
<Chapter2_ID>8</Chapter2_ID>
<Track_Number>8</Track_Number>
<Track_Name>Track 8</Track_Name>
<Track_File_Name>TOEFL_iBT_08.mp3</Track_File_Name>
<Track_Image>06.png</Track_Image>
</Chapter2>
<Chapter2>
<Chapter2_ID>9</Chapter2_ID>
<Track_Number>9</Track_Number>
<Track_Name>Track 9</Track_Name>
<Track_File_Name>TOEFL_iBT_09.mp3</Track_File_Name>
<Track_Image>00.png</Track_Image>
</Chapter2>
<Chapter2>
<Chapter2_ID>10</Chapter2_ID>
<Track_Number>10</Track_Number>
<Track_Name>Track 10</Track_Name>
<Track_File_Name>TOEFL_iBT_10.mp3</Track_File_Name>
<Track_Image>00.png</Track_Image>
</Chapter2>
<Chapter2>
<Chapter2_ID>11</Chapter2_ID>
<Track_Number>11</Track_Number>
<Track_Name>Track 11</Track_Name>
<Track_File_Name>TOEFL_iBT_11.mp3</Track_File_Name>
<Track_Image>00.png</Track_Image>
</Chapter2>
<Chapter2>
<Chapter2_ID>12</Chapter2_ID>
<Track_Number>12</Track_Number>
<Track_Name>Track 12</Track_Name>
<Track_File_Name>TOEFL_iBT_12.mp3</Track_File_Name>
<Track_Image>18.png</Track_Image>
</Chapter2>
<Chapter2>
<Chapter2_ID>13</Chapter2_ID>
<Track_Number>13</Track_Number>
<Track_Name>Track 13</Track_Name>
<Track_File_Name>TOEFL_iBT_13.mp3</Track_File_Name>
<Track_Image>00.png</Track_Image>
</Chapter2>
<Chapter2>
<Chapter2_ID>14</Chapter2_ID>
<Track_Number>14</Track_Number>
<Track_Name>Track 14</Track_Name>
<Track_File_Name>TOEFL_iBT_14.mp3</Track_File_Name>
<Track_Image>19.png</Track_Image>
</Chapter2>
<Chapter2>
<Chapter2_ID>15</Chapter2_ID>
<Track_Number>15</Track_Number>
<Track_Name>Track 15</Track_Name>
<Track_File_Name>TOEFL_iBT_15.mp3</Track_File_Name>
<Track_Image>20.png</Track_Image>
</Chapter2>
<Chapter2>
<Chapter2_ID>16</Chapter2_ID>
<Track_Number>16</Track_Number>
<Track_Name>Track 16</Track_Name>
<Track_File_Name>TOEFL_iBT_16.mp3</Track_File_Name>
<Track_Image>21.png</Track_Image>
</Chapter2>
<Chapter2>
<Chapter2_ID>17</Chapter2_ID>
<Track_Number>17</Track_Number>
<Track_Name>Track 17</Track_Name>
<Track_File_Name>TOEFL_iBT_17.mp3</Track_File_Name>
<Track_Image>31.png</Track_Image>
</Chapter2>
<Chapter2>
<Chapter2_ID>18</Chapter2_ID>
<Track_Number>18</Track_Number>
<Track_Name>Track 18</Track_Name>
<Track_File_Name>TOEFL_iBT_18.mp3</Track_File_Name>
<Track_Image>00.png</Track_Image>
</Chapter2>
<Chapter2>
<Chapter2_ID>19</Chapter2_ID>
<Track_Number>19</Track_Number>
<Track_Name>Track 19</Track_Name>
<Track_File_Name>TOEFL_iBT_19.mp3</Track_File_Name>
<Track_Image>00.png</Track_Image>
</Chapter2>
<Chapter2>
<Chapter2_ID>20</Chapter2_ID>
<Track_Number>20</Track_Number>
<Track_Name>Track 20</Track_Name>
<Track_File_Name>TOEFL_iBT_20.mp3</Track_File_Name>
<Track_Image>00.png</Track_Image>
</Chapter2>
<Chapter2>
<Chapter2_ID>21</Chapter2_ID>
<Track_Number>21</Track_Number>
<Track_Name>Track 21</Track_Name>
<Track_File_Name>TOEFL_iBT_21.mp3</Track_File_Name>
<Track_Image>00.png</Track_Image>
</Chapter2>
<Chapter2>
<Chapter2_ID>22</Chapter2_ID>
<Track_Number>22</Track_Number>
<Track_Name>Track 22</Track_Name>
<Track_File_Name>TOEFL_iBT_22.mp3</Track_File_Name>
<Track_Image>00.png</Track_Image>
</Chapter2>
<Chapter2>
<Chapter2_ID>23</Chapter2_ID>
<Track_Number>23</Track_Number>
<Track_Name>Track 23</Track_Name>
<Track_File_Name>TOEFL_iBT_23.mp3</Track_File_Name>
<Track_Image>00.png</Track_Image>
</Chapter2>
<Chapter2>
<Chapter2_ID>24</Chapter2_ID>
<Track_Number>24</Track_Number>
<Track_Name>Track 24</Track_Name>
<Track_File_Name>TOEFL_iBT_24.mp3</Track_File_Name>
<Track_Image>00.png</Track_Image>
</Chapter2>
</dataroot>
